sh2mp4/__init__.py
sh2mp4/__main__.py
sh2mp4/args.py
sh2mp4/ascii_preview.py
sh2mp4/asciicast.py
sh2mp4/check_deps.py
sh2mp4/display.py
sh2mp4/fonts.py
sh2mp4/measure_fonts.py
sh2mp4/peep.py
sh2mp4/recorder.py
sh2mp4/terminal.py
sh2mp4/themes.py
sh2mp4/xserver.py
sh2mp4-0.3.5.dist-info/entry_points.txt
sh2mp4-0.3.5.dist-info/licenses/LICENSE.md
sh2mp4-0.3.5.dist-info/WHEEL
sh2mp4-0.3.5.dist-info/METADATA
sh2mp4-0.3.5.dist-info/RECORD
