Metadata-Version: 2.4
Name: sh2mp4
Version: 0.3.5
Summary: Records shell commands to MP4 videos
Author-email: Gareth Davidson <gaz@bitplane.net>
Requires-Python: >=3.10
License-File: LICENSE.md
Requires-Dist: Pillow>=9.0.0
Requires-Dist: pytk
Requires-Dist: pre-commit ; extra == "dev"
Requires-Dist: pytest ; extra == "dev"
Requires-Dist: coverage ; extra == "dev"
Requires-Dist: pytest-cov ; extra == "dev"
Requires-Dist: pytest-asyncio ; extra == "dev"
Requires-Dist: build ; extra == "dev"
Requires-Dist: twine ; extra == "dev"
Requires-Dist: ruff ; extra == "dev"
Requires-Dist: pydoc-markdown ; extra == "dev"
Provides-Extra: dev
